{
	"$schema": "http://schema.management.azure.com/schemas/2015-01-01/deploymentTemplate.json#",
	"contentVersion": "1.0.0.0",
	"parameters": {
		"factoryName": {
			"type": "string",
			"metadata": "Data Factory name",
			"defaultValue": "simha12326"
		}
	},
	"variables": {
		"factoryId": "[concat('Microsoft.DataFactory/factories/', parameters('factoryName'))]"
	},
	"resources": [
		{
			"name": "[concat(parameters('factoryName'), '/Json6')]",
			"type": "Microsoft.DataFactory/factories/datasets",
			"apiVersion": "2018-06-01",
			"properties": {
				"linkedServiceName": {
					"referenceName": "AzureDataLakeStorage1",
					"type": "LinkedServiceReference"
				},
				"annotations": [],
				"type": "Json",
				"typeProperties": {
					"location": {
						"type": "AzureBlobFSLocation",
						"fileSystem": "targetcontainer123"
					}
				},
				"schema": {}
			},
			"dependsOn": []
		},
		{
			"name": "[concat(parameters('factoryName'), '/DelimitedText8')]",
			"type": "Microsoft.DataFactory/factories/datasets",
			"apiVersion": "2018-06-01",
			"properties": {
				"linkedServiceName": {
					"referenceName": "AzureDataLakeStorage1",
					"type": "LinkedServiceReference"
				},
				"annotations": [],
				"type": "DelimitedText",
				"typeProperties": {
					"location": {
						"type": "AzureBlobFSLocation",
						"fileName": "addresses (1).csv",
						"fileSystem": "confusion1"
					},
					"columnDelimiter": ",",
					"escapeChar": "\\",
					"firstRowAsHeader": true,
					"quoteChar": "\""
				},
				"schema": [
					{
						"name": "FirstName",
						"type": "String"
					},
					{
						"name": "LastName",
						"type": "String"
					},
					{
						"name": "AddressLine",
						"type": "String"
					},
					{
						"name": "City",
						"type": "String"
					},
					{
						"name": "State",
						"type": "String"
					},
					{
						"name": "ZipCode",
						"type": "String"
					}
				]
			},
			"dependsOn": []
		},
		{
			"name": "[concat(parameters('factoryName'), '/DelimitedText9')]",
			"type": "Microsoft.DataFactory/factories/datasets",
			"apiVersion": "2018-06-01",
			"properties": {
				"linkedServiceName": {
					"referenceName": "AzureDataLakeStorage1",
					"type": "LinkedServiceReference"
				},
				"annotations": [],
				"type": "DelimitedText",
				"typeProperties": {
					"location": {
						"type": "AzureBlobFSLocation",
						"fileSystem": "archeives1"
					},
					"columnDelimiter": ",",
					"escapeChar": "\\",
					"firstRowAsHeader": true,
					"quoteChar": "\""
				},
				"schema": [
					{
						"name": "FirstName",
						"type": "String"
					},
					{
						"name": "LastName",
						"type": "String"
					},
					{
						"name": "AddressLine",
						"type": "String"
					},
					{
						"name": "City",
						"type": "String"
					},
					{
						"name": "State",
						"type": "String"
					},
					{
						"name": "ZipCode",
						"type": "String"
					}
				]
			},
			"dependsOn": []
		},
		{
			"name": "[concat(parameters('factoryName'), '/Binary4')]",
			"type": "Microsoft.DataFactory/factories/datasets",
			"apiVersion": "2018-06-01",
			"properties": {
				"linkedServiceName": {
					"referenceName": "AzureDataLakeStorage1",
					"type": "LinkedServiceReference"
				},
				"annotations": [],
				"type": "Binary",
				"typeProperties": {
					"location": {
						"type": "AzureBlobFSLocation",
						"fileName": "addresses (1).csv",
						"fileSystem": "confusion1"
					}
				}
			},
			"dependsOn": []
		},
		{
			"name": "[concat(parameters('factoryName'), '/tensionparty1')]",
			"type": "Microsoft.DataFactory/factories/pipelines",
			"apiVersion": "2018-06-01",
			"properties": {
				"activities": [
					{
						"name": "Copy data1",
						"description": "i need copy data from 1 container to other",
						"type": "Copy",
						"dependsOn": [],
						"policy": {
							"timeout": "0.12:00:00",
							"retry": 0,
							"retryIntervalInSeconds": 30,
							"secureOutput": false,
							"secureInput": false
						},
						"userProperties": [
							{
								"name": "Source",
								"value": "students-datas//sales_practice_dataset.csv"
							}
						],
						"typeProperties": {
							"source": {
								"type": "DelimitedTextSource",
								"additionalColumns": [
									{
										"value": "$$FILEPATH"
									},
									{
										"value": "$$FILEPATH"
									}
								],
								"storeSettings": {
									"type": "AzureBlobFSReadSettings",
									"recursive": true,
									"modifiedDatetimeStart": "2026-03-10T00:00:00.000Z",
									"modifiedDatetimeEnd": "2026-03-31T00:00:00.000Z",
									"enablePartitionDiscovery": false
								},
								"formatSettings": {
									"type": "DelimitedTextReadSettings"
								}
							},
							"sink": {
								"type": "JsonSink",
								"storeSettings": {
									"type": "AzureBlobFSWriteSettings"
								},
								"formatSettings": {
									"type": "JsonWriteSettings"
								}
							},
							"enableStaging": false
						},
						"inputs": [
							{
								"referenceName": "ADLSSourceLinkedService",
								"type": "DatasetReference",
								"parameters": {}
							}
						],
						"outputs": [
							{
								"referenceName": "Json3",
								"type": "DatasetReference",
								"parameters": {}
							}
						]
					},
					{
						"name": "Delete1",
						"type": "Delete",
						"dependsOn": [],
						"policy": {
							"timeout": "0.12:00:00",
							"retry": 0,
							"retryIntervalInSeconds": 30,
							"secureOutput": false,
							"secureInput": false
						},
						"userProperties": [],
						"typeProperties": {
							"dataset": {
								"referenceName": "Binary1",
								"type": "DatasetReference",
								"parameters": {}
							},
							"logStorageSettings": {
								"linkedServiceName": {
									"referenceName": "AzureDataLakeStorage1",
									"type": "LinkedServiceReference"
								}
							},
							"enableLogging": true,
							"storeSettings": {
								"type": "AzureBlobFSReadSettings",
								"recursive": true,
								"enablePartitionDiscovery": false
							}
						}
					},
					{
						"name": "Copy data2",
						"type": "Copy",
						"dependsOn": [],
						"policy": {
							"timeout": "0.12:00:00",
							"retry": 0,
							"retryIntervalInSeconds": 30,
							"secureOutput": false,
							"secureInput": false
						},
						"userProperties": [],
						"typeProperties": {
							"enableStaging": false
						}
					},
					{
						"name": "Copy activity3",
						"description": "i need copy data from 1 container to other",
						"type": "Copy",
						"dependsOn": [],
						"policy": {
							"timeout": "0.12:00:00",
							"retry": 0,
							"retryIntervalInSeconds": 30,
							"secureOutput": false,
							"secureInput": false
						},
						"userProperties": [],
						"typeProperties": {
							"source": {
								"type": "DelimitedTextSource",
								"storeSettings": {
									"type": "AzureBlobFSReadSettings",
									"recursive": true,
									"enablePartitionDiscovery": false
								},
								"formatSettings": {
									"type": "DelimitedTextReadSettings"
								}
							},
							"sink": {
								"type": "JsonSink",
								"storeSettings": {
									"type": "AzureBlobFSWriteSettings"
								},
								"formatSettings": {
									"type": "JsonWriteSettings"
								}
							},
							"enableStaging": false
						},
						"inputs": [
							{
								"referenceName": "ADLSSourceLinkedService",
								"type": "DatasetReference",
								"parameters": {}
							}
						],
						"outputs": [
							{
								"referenceName": "Json4",
								"type": "DatasetReference",
								"parameters": {}
							}
						]
					},
					{
						"name": "Delete2",
						"type": "Delete",
						"dependsOn": [],
						"policy": {
							"timeout": "0.12:00:00",
							"retry": 0,
							"retryIntervalInSeconds": 30,
							"secureOutput": false,
							"secureInput": false
						},
						"userProperties": [],
						"typeProperties": {
							"dataset": {
								"referenceName": "Binary2",
								"type": "DatasetReference",
								"parameters": {}
							},
							"logStorageSettings": {
								"linkedServiceName": {
									"referenceName": "AzureDataLakeStorage16",
									"type": "LinkedServiceReference"
								}
							},
							"enableLogging": true,
							"storeSettings": {
								"type": "AzureBlobFSReadSettings",
								"recursive": true,
								"modifiedDatetimeStart": "2026-03-10T00:00:00.000Z",
								"modifiedDatetimeEnd": "2026-04-30T00:00:00.000Z",
								"enablePartitionDiscovery": false
							}
						}
					}
				],
				"policy": {
					"elapsedTimeMetric": {}
				},
				"annotations": []
			},
			"dependsOn": []
		},
		{
			"name": "[concat(parameters('factoryName'), '/pipeline1')]",
			"type": "Microsoft.DataFactory/factories/pipelines",
			"apiVersion": "2018-06-01",
			"properties": {
				"activities": [
					{
						"name": "Copy data2",
						"type": "Copy",
						"dependsOn": [],
						"policy": {
							"timeout": "0.12:00:00",
							"retry": 0,
							"retryIntervalInSeconds": 30,
							"secureOutput": false,
							"secureInput": false
						},
						"userProperties": [],
						"typeProperties": {
							"enableStaging": false
						}
					},
					{
						"name": "Copy activity3",
						"type": "Copy",
						"dependsOn": [],
						"policy": {
							"timeout": "0.12:00:00",
							"retry": 0,
							"retryIntervalInSeconds": 30,
							"secureOutput": false,
							"secureInput": false
						},
						"userProperties": [],
						"typeProperties": {
							"enableStaging": false
						}
					},
					{
						"name": "Copy data3",
						"type": "Copy",
						"dependsOn": [],
						"policy": {
							"timeout": "0.12:00:00",
							"retry": 0,
							"retryIntervalInSeconds": 30,
							"secureOutput": false,
							"secureInput": false
						},
						"userProperties": [],
						"typeProperties": {
							"source": {
								"type": "DelimitedTextSource",
								"storeSettings": {
									"type": "AzureBlobFSReadSettings",
									"recursive": true,
									"enablePartitionDiscovery": false
								},
								"formatSettings": {
									"type": "DelimitedTextReadSettings"
								}
							},
							"sink": {
								"type": "JsonSink",
								"storeSettings": {
									"type": "AzureBlobFSWriteSettings"
								},
								"formatSettings": {
									"type": "JsonWriteSettings"
								}
							},
							"enableStaging": false
						},
						"inputs": [
							{
								"referenceName": "DelimitedText7",
								"type": "DatasetReference",
								"parameters": {}
							}
						],
						"outputs": [
							{
								"referenceName": "Json6",
								"type": "DatasetReference",
								"parameters": {}
							}
						]
					},
					{
						"name": "Copy data4",
						"type": "Copy",
						"dependsOn": [],
						"policy": {
							"timeout": "0.12:00:00",
							"retry": 0,
							"retryIntervalInSeconds": 30,
							"secureOutput": false,
							"secureInput": false
						},
						"userProperties": [],
						"typeProperties": {
							"source": {
								"type": "DelimitedTextSource",
								"storeSettings": {
									"type": "AzureBlobFSReadSettings",
									"recursive": true,
									"enablePartitionDiscovery": false
								},
								"formatSettings": {
									"type": "DelimitedTextReadSettings"
								}
							},
							"sink": {
								"type": "DelimitedTextSink",
								"storeSettings": {
									"type": "AzureBlobFSWriteSettings"
								},
								"formatSettings": {
									"type": "DelimitedTextWriteSettings",
									"quoteAllText": true,
									"fileExtension": ".txt"
								}
							},
							"enableStaging": false,
							"translator": {
								"type": "TabularTranslator",
								"typeConversion": true,
								"typeConversionSettings": {
									"allowDataTruncation": true,
									"treatBooleanAsNumber": false
								}
							}
						},
						"inputs": [
							{
								"referenceName": "DelimitedText8",
								"type": "DatasetReference",
								"parameters": {}
							}
						],
						"outputs": [
							{
								"referenceName": "DelimitedText9",
								"type": "DatasetReference",
								"parameters": {}
							}
						]
					},
					{
						"name": "Delete1",
						"type": "Delete",
						"dependsOn": [],
						"policy": {
							"timeout": "0.12:00:00",
							"retry": 0,
							"retryIntervalInSeconds": 30,
							"secureOutput": false,
							"secureInput": false
						},
						"userProperties": [],
						"typeProperties": {
							"dataset": {
								"referenceName": "Binary4",
								"type": "DatasetReference",
								"parameters": {}
							},
							"logStorageSettings": {
								"linkedServiceName": {
									"referenceName": "AzureDataLakeStorage1",
									"type": "LinkedServiceReference"
								}
							},
							"enableLogging": true,
							"storeSettings": {
								"type": "AzureBlobFSReadSettings",
								"recursive": true,
								"enablePartitionDiscovery": false
							}
						}
					}
				],
				"policy": {
					"elapsedTimeMetric": {}
				},
				"annotations": []
			},
			"dependsOn": [
				"[concat(variables('factoryId'), '/datasets/Json6')]",
				"[concat(variables('factoryId'), '/datasets/DelimitedText8')]",
				"[concat(variables('factoryId'), '/datasets/DelimitedText9')]",
				"[concat(variables('factoryId'), '/datasets/Binary4')]"
			]
		}
	]
}